XStatic_Angular_FileUpload-12.2.13.0-nspkg.pth
xstatic/pkg/angular_fileupload/__init__.py
xstatic/pkg/angular_fileupload/data/FileAPI.flash.swf
xstatic/pkg/angular_fileupload/data/FileAPI.js
xstatic/pkg/angular_fileupload/data/FileAPI.min.js
xstatic/pkg/angular_fileupload/data/ng-file-upload-all.js
xstatic/pkg/angular_fileupload/data/ng-file-upload-all.min.js
xstatic/pkg/angular_fileupload/data/ng-file-upload-shim.js
xstatic/pkg/angular_fileupload/data/ng-file-upload-shim.min.js
xstatic/pkg/angular_fileupload/data/ng-file-upload.js
xstatic/pkg/angular_fileupload/data/ng-file-upload.min.js
XStatic_Angular_FileUpload-12.2.13.0.dist-info/LICENCE
XStatic_Angular_FileUpload-12.2.13.0.dist-info/METADATA
XStatic_Angular_FileUpload-12.2.13.0.dist-info/WHEEL
XStatic_Angular_FileUpload-12.2.13.0.dist-info/namespace_packages.txt
XStatic_Angular_FileUpload-12.2.13.0.dist-info/top_level.txt
XStatic_Angular_FileUpload-12.2.13.0.dist-info/RECORD
