Metadata-Version: 2.1
Name: XStatic-Angular-FileUpload
Version: 12.2.13.0
Summary: Angular-FileUpload 12.2.13 (XStatic packaging standard)
Home-page: https://github.com/danialfarid/angular-file-upload
Maintainer: Radomir Dopieralski
Maintainer-email: openstack@sheep.art.pl
License: (same as Angular-FileUpload)
Keywords: angular_fileupload xstatic
Platform: any
